README.md
setup.py
WriteProMD.egg-info/PKG-INFO
WriteProMD.egg-info/SOURCES.txt
WriteProMD.egg-info/dependency_links.txt
WriteProMD.egg-info/entry_points.txt
WriteProMD.egg-info/requires.txt
WriteProMD.egg-info/top_level.txt
writepromd/MarkdownToPDFParser.py
writepromd/PDF.py
writepromd/__init__.py
writepromd/__main__.py
writepromd/writepromd.py